mkdocs_jupyterlite/__init__.py
mkdocs_jupyterlite/_build.py
mkdocs_jupyterlite/_plugin.py
mkdocs_jupyterlite/py.typed
mkdocs_jupyterlite/static/iframe-scroll-handler.js
mkdocs_jupyterlite/static/toc-handler.js
mkdocs_jupyterlite-0.4.1.dist-info/METADATA
mkdocs_jupyterlite-0.4.1.dist-info/WHEEL
mkdocs_jupyterlite-0.4.1.dist-info/entry_points.txt
mkdocs_jupyterlite-0.4.1.dist-info/licenses/LICENSE
mkdocs_jupyterlite-0.4.1.dist-info/RECORD
