Metadata-Version: 2.4
Name: mkdocs-jupyterlite
Version: 0.4.1
Summary: Embed interactive notebooks in your MkDocs site using JupyterLite.
Project-URL: Documentation, https://github.com/NickCrews/mkdocs-jupyterlite#readme
Project-URL: Homepage, https://github.com/NickCrews/mkdocs-jupyterlite
Project-URL: Source, https://github.com/NickCrews/mkdocs-jupyterlite
Project-URL: Tracker, https://github.com/NickCrews/mkdocs-jupyterlite/issues
Author-email: Nick Crews <nicholas.b.crews@gmail.com>
License-File: LICENSE
Requires-Python: >=3.9
Requires-Dist: gitmatch>=0.2.1
Requires-Dist: jupyterlab-server>=2.27.3
Requires-Dist: jupyterlite-core>=0.6.4
Requires-Dist: jupyterlite-pyodide-kernel>=0.6.1
Requires-Dist: mkdocs>=1.6.1
